[
   {
      "type" : "AMMO",
      "id" : "kawaii_arrow_ribbon",
      "name" : "矢(リボン)[kawaii]",
      "description" : "リボンの装飾を付けた矢です。あえて手間を掛け可愛く仕上げる事で愛着が沸き、無駄にしたくない気持ちを利用する事で高い回収率を実現した高度な心理作戦です。色柄物の布を可愛い部分だけ使う為、布を贅沢に消費します。",
      "copy-from": "arrow_wood",
      "effects" : ["RECOVER_50"]
   },
   {
      "type" : "AMMO",
      "id" : "kawaii_arrow_feather",
      "name" : "矢(フェザー)[kawaii]",
      "description" : "シャープなシルエットと美しい羽の装飾が目を引く矢です。非常に軽く細い為に一見頼りない様に見えますが、生物や機械の構造を理解する事で対象の弱点を的確に射貫き、致命傷を与える事が出来ます。医学や機械の知識、そして射手として十分な腕と経験が無ければこの発想は生まれなかったでしょう。",
      "copy-from": "arrow_metal_bodkin",
      "effects" : ["RECOVER_80"]
   },
   {
      "type" : "AMMO",
      "id" : "kawaii_arrow_little_mary",
      "name" : "矢(LittleMary)[kawaii]",
      "description" : "【Alice & Maria】ブランドの矢です。同ブランドの弓【SHELIA】と同時に発表され、消耗品にも関わらず超小型のタッチディスプレイを搭載し、周囲に纏った電磁ブレードの形状を適切に調整する事であらゆる対象に別次元の威力を発揮します。",
      "copy-from": "arrow_cf",
      "effects" : ["RECOVER_80"]
   }
]